{
    "model_name": "logite_baseline-wx_8_mor",
    "meta_runtime": 1.1070442199707031,
    "meta_trainval_counts": [
        [
            3487,
            896
        ],
        [
            4362,
            1067
        ],
        [
            6530,
            1675
        ],
        [
            1880,
            447
        ],
        [
            4281,
            1098
        ],
        [
            4889,
            1225
        ],
        [
            6605,
            1649
        ],
        [
            3049,
            739
        ],
        [
            6308,
            1620
        ],
        [
            4383,
            1079
        ],
        [
            6329,
            1518
        ],
        [
            1981,
            511
        ]
    ],
    "perf_model_accuracy_train": 0.34045188965313217,
    "perf_f1_train": [
        0.24954364866315903,
        0.16361231815605518,
        0.48153122901276024,
        0.17737580993520516,
        0.1385329619312906,
        0.1450488145048815,
        0.2468265162200282,
        0.20998455995882656,
        0.15773576462691577,
        0.6173745413842423,
        0.15275890187550964,
        0.5887901324142935
    ],
    "perf_macro_f1_w_train": 0.303309017040481,
    "perf_macro_f1_avg_train": 0.27742626655693065,
    "perf_confusion_train": [
        [
            373,
            348,
            1245,
            215,
            31,
            275,
            159,
            198,
            92,
            191,
            242,
            118
        ],
        [
            285,
            657,
            795,
            337,
            44,
            258,
            256,
            239,
            178,
            650,
            545,
            118
        ],
        [
            324,
            280,
            4964,
            104,
            19,
            218,
            118,
            112,
            58,
            85,
            171,
            77
        ],
        [
            132,
            171,
            310,
            525,
            14,
            86,
            49,
            152,
            23,
            204,
            138,
            76
        ],
        [
            0,
            2,
            2,
            6,
            3246,
            8,
            953,
            3,
            48,
            1,
            12,
            0
        ],
        [
            248,
            234,
            528,
            184,
            272,
            562,
            918,
            234,
            357,
            479,
            696,
            177
        ],
        [
            7,
            10,
            34,
            18,
            1621,
            78,
            4302,
            6,
            345,
            30,
            151,
            3
        ],
        [
            144,
            223,
            452,
            268,
            40,
            169,
            175,
            433,
            102,
            499,
            349,
            195
        ],
        [
            43,
            108,
            144,
            87,
            1032,
            221,
            2957,
            59,
            705,
            282,
            579,
            91
        ],
        [
            94,
            411,
            343,
            304,
            75,
            113,
            330,
            356,
            185,
            1162,
            788,
            222
        ],
        [
            168,
            486,
            538,
            248,
            337,
            411,
            964,
            255,
            486,
            945,
            1224,
            267
        ],
        [
            80,
            116,
            196,
            78,
            14,
            70,
            82,
            197,
            52,
            402,
            434,
            260
        ]
    ],
    "perf_kappa_train": 0.2695223578504514,
    "perf_within_class_accuracy_train": [
        0.10696874103814166,
        0.15061898211829436,
        0.7601837672281776,
        0.27925531914893614,
        0.7582340574632095,
        0.11495193291061567,
        0.6513247539742619,
        0.14201377500819942,
        0.11176284083703233,
        0.2651152178872918,
        0.19339548111866015,
        0.13124684502776376
    ],
    "perf_model_accuracy_val": 0.3347382431233363,
    "perf_f1_val": [
        0.22522915757311218,
        0.15719844357976653,
        0.466394187102634,
        0.17094017094017092,
        0.15558698727015557,
        0.1628440366972477,
        0.23008849557522124,
        0.18611309949892627,
        0.17523167649536647,
        0.6061199510403916,
        0.15303430079155672,
        0.6061930783242258
    ],
    "perf_macro_f1_w_val": 0.3010093778501105,
    "perf_macro_f1_avg_val": 0.2745811320740646,
    "perf_confusion_val": [
        [
            110,
            96,
            310,
            58,
            7,
            70,
            41,
            55,
            12,
            64,
            59,
            14
        ],
        [
            84,
            160,
            190,
            86,
            9,
            67,
            61,
            75,
            28,
            152,
            136,
            19
        ],
        [
            104,
            80,
            1238,
            29,
            5,
            75,
            15,
            19,
            11,
            22,
            51,
            26
        ],
        [
            26,
            45,
            76,
            117,
            5,
            25,
            17,
            33,
            5,
            52,
            30,
            16
        ],
        [
            0,
            1,
            6,
            3,
            832,
            1,
            242,
            0,
            11,
            1,
            1,
            0
        ],
        [
            53,
            68,
            124,
            49,
            65,
            145,
            222,
            63,
            114,
            103,
            171,
            48
        ],
        [
            0,
            4,
            17,
            5,
            378,
            26,
            1027,
            0,
            140,
            12,
            38,
            2
        ],
        [
            29,
            71,
            114,
            56,
            6,
            39,
            43,
            101,
            23,
            138,
            83,
            36
        ],
        [
            9,
            30,
            78,
            19,
            250,
            53,
            730,
            19,
            208,
            74,
            134,
            16
        ],
        [
            39,
            110,
            88,
            63,
            21,
            33,
            99,
            67,
            47,
            258,
            206,
            48
        ],
        [
            45,
            111,
            125,
            60,
            61,
            108,
            235,
            69,
            133,
            246,
            260,
            65
        ],
        [
            19,
            29,
            44,
            25,
            8,
            28,
            23,
            45,
            22,
            90,
            107,
            71
        ]
    ],
    "perf_kappa_val": 0.2628307752404174,
    "perf_within_class_accuracy_val": [
        0.12276785714285714,
        0.14995313964386128,
        0.7391044776119403,
        0.26174496644295303,
        0.7577413479052824,
        0.11836734693877551,
        0.6228016979987872,
        0.13667117726657646,
        0.12839506172839507,
        0.2391102873030584,
        0.1712779973649539,
        0.13894324853228962
    ],
    "meta_class_names": [
        "dense_urban_neighbourhoods",
        "dense_residential_neighbourhoods",
        "urbanity",
        "gridded_residential_quarters",
        "wild_countryside",
        "warehouse_park_land",
        "countryside_agriculture",
        "connected_residential_neighbourhoods",
        "urban_buffer",
        "accessible_suburbia",
        "open_sprawl",
        "disconnected_suburbia"
    ],
    "meta_n_class": 12,
    "meta_preds_path": "/home/jovyan/data/spatial_signatures/chip_probs/prod_model_outputs/",
    "model_params": {
        "coefs": [
            {
                "urbanity": 0.03231377522771314,
                "dense_urban_neighbourhoods": 0.15490435151428716,
                "dense_residential_neighbourhoods": 0.03924145531354212,
                "connected_residential_neighbourhoods": 0.045116737490090354,
                "gridded_residential_quarters": 0.04289131174111858,
                "accessible_suburbia": 0.005406186962188281,
                "disconnected_suburbia": 0.012339647219200445,
                "open_sprawl": -0.0006761843771085152,
                "warehouse_park_land": 0.026933406612888403,
                "urban_buffer": 0.031535997801232014,
                "countryside_agriculture": 0.044374180347103984,
                "wild_countryside": 0.06065082858552639,
                "w_urbanity": -0.12062322722904202,
                "w_dense_urban_neighbourhoods": 0.13076511585863257,
                "w_dense_residential_neighbourhoods": -0.013274748711144415,
                "w_connected_residential_neighbourhoods": 0.0043349596464132825,
                "w_gridded_residential_quarters": -0.025948006217794913,
                "w_accessible_suburbia": -0.04750083515520002,
                "w_disconnected_suburbia": -0.0327894324806433,
                "w_open_sprawl": -0.03185319656594074,
                "w_warehouse_park_land": -0.010993885688047392,
                "w_urban_buffer": -0.03411056215574491,
                "w_countryside_agriculture": -0.042642362423416756,
                "w_wild_countryside": -0.0671588237962291
            },
            {
                "urbanity": 0.024546759194245562,
                "dense_urban_neighbourhoods": -0.00492530299028165,
                "dense_residential_neighbourhoods": 0.18171958193065746,
                "connected_residential_neighbourhoods": 0.00837791114238184,
                "gridded_residential_quarters": 0.058412192731671676,
                "accessible_suburbia": 0.04341301199229721,
                "disconnected_suburbia": -0.015161113268781992,
                "open_sprawl": -0.02366475077384986,
                "warehouse_park_land": 0.027621992977997136,
                "urban_buffer": 0.027695686006348672,
                "countryside_agriculture": 0.017899943849088232,
                "wild_countryside": 0.04846875209366429,
                "w_urbanity": 0.0885844961961286,
                "w_dense_urban_neighbourhoods": 0.04479462478309009,
                "w_dense_residential_neighbourhoods": 0.191495440084473,
                "w_connected_residential_neighbourhoods": 0.044144690329099116,
                "w_gridded_residential_quarters": 0.10355344396778536,
                "w_accessible_suburbia": 0.08590594113414064,
                "w_disconnected_suburbia": 0.03073531030657509,
                "w_open_sprawl": 0.009361017061896001,
                "w_warehouse_park_land": 0.0465106820957723,
                "w_urban_buffer": 0.0789842986654547,
                "w_countryside_agriculture": 0.09467657968863018,
                "w_wild_countryside": 0.14952440726225538
            },
            {
                "urbanity": 0.48676376811191374,
                "dense_urban_neighbourhoods": -0.7957005884493735,
                "dense_residential_neighbourhoods": -0.42090872270159435,
                "connected_residential_neighbourhoods": -0.29261161128424534,
                "gridded_residential_quarters": -0.5911038403703839,
                "accessible_suburbia": -0.3532147017342097,
                "disconnected_suburbia": -0.49202145595046637,
                "open_sprawl": -0.17458687868063275,
                "warehouse_park_land": -0.37696179644006717,
                "urban_buffer": -0.6113818063028768,
                "countryside_agriculture": -0.7662707333368893,
                "wild_countryside": -1.1252833869462364,
                "w_urbanity": 1.171174468067279,
                "w_dense_urban_neighbourhoods": -0.6150628271993396,
                "w_dense_residential_neighbourhoods": -0.17516212401977863,
                "w_connected_residential_neighbourhoods": -0.08951124218656417,
                "w_gridded_residential_quarters": -0.23275660708484477,
                "w_accessible_suburbia": -0.08550870482877433,
                "w_disconnected_suburbia": -0.288761707750069,
                "w_open_sprawl": -0.048437539469914574,
                "w_warehouse_park_land": -0.12076002692752001,
                "w_urban_buffer": -0.2628729027441152,
                "w_countryside_agriculture": -0.29088726476552734,
                "w_wild_countryside": -0.4448729038423284
            },
            {
                "urbanity": -0.24803092537476912,
                "dense_urban_neighbourhoods": -0.0950100712867185,
                "dense_residential_neighbourhoods": -0.09638584046511234,
                "connected_residential_neighbourhoods": -0.0638759885342251,
                "gridded_residential_quarters": -0.01730488576472388,
                "accessible_suburbia": -0.13863501209651652,
                "disconnected_suburbia": -0.08755647687919768,
                "open_sprawl": -0.07112078701344797,
                "warehouse_park_land": -0.10970405935551295,
                "urban_buffer": -0.1395344589025184,
                "countryside_agriculture": -0.2042066674100683,
                "wild_countryside": -0.2856154832933098,
                "w_urbanity": -0.22671791494044555,
                "w_dense_urban_neighbourhoods": -0.08279251485738261,
                "w_dense_residential_neighbourhoods": -0.09431143124259884,
                "w_connected_residential_neighbourhoods": -0.07376338812365556,
                "w_gridded_residential_quarters": 0.004410560852756348,
                "w_accessible_suburbia": -0.1330724120176132,
                "w_disconnected_suburbia": -0.06954997174571859,
                "w_open_sprawl": -0.0592545776283189,
                "w_warehouse_park_land": -0.09236079358699581,
                "w_urban_buffer": -0.12875843284538027,
                "w_countryside_agriculture": -0.17571529547593825,
                "w_wild_countryside": -0.2560306525503795
            },
            {
                "urbanity": -0.7017673655810257,
                "dense_urban_neighbourhoods": -0.29128409315858966,
                "dense_residential_neighbourhoods": -0.29487387424972294,
                "connected_residential_neighbourhoods": -0.23384134056673175,
                "gridded_residential_quarters": -0.47071373704380115,
                "accessible_suburbia": -0.32170687396124636,
                "disconnected_suburbia": -0.27828906239763235,
                "open_sprawl": -0.15982050245189602,
                "warehouse_park_land": -0.3043489929946734,
                "urban_buffer": -0.2960841276709038,
                "countryside_agriculture": -1.0178865497061282,
                "wild_countryside": 0.04929582017338645,
                "w_urbanity": -0.7838203937607799,
                "w_dense_urban_neighbourhoods": -0.34528821750915667,
                "w_dense_residential_neighbourhoods": -0.33636207809501545,
                "w_connected_residential_neighbourhoods": -0.2702424938474319,
                "w_gridded_residential_quarters": -0.5525838067183411,
                "w_accessible_suburbia": -0.3841811921042849,
                "w_disconnected_suburbia": -0.31777988173230565,
                "w_open_sprawl": -0.18037480997378752,
                "w_warehouse_park_land": -0.35366972120127455,
                "w_urban_buffer": -0.3490990322070423,
                "w_countryside_agriculture": -1.1240290047947814,
                "w_wild_countryside": 0.019827499211384176
            },
            {
                "urbanity": -0.04302913665968659,
                "dense_urban_neighbourhoods": 0.017384132527006622,
                "dense_residential_neighbourhoods": -0.048422103456694614,
                "connected_residential_neighbourhoods": 0.016154056358639358,
                "gridded_residential_quarters": -0.02108524351211539,
                "accessible_suburbia": -0.014370660198266,
                "disconnected_suburbia": -0.016037745159846385,
                "open_sprawl": 0.021698415714438937,
                "warehouse_park_land": 0.11700844584817034,
                "urban_buffer": -0.025590457742957682,
                "countryside_agriculture": -0.026753031105143276,
                "wild_countryside": -0.024416069766881588,
                "w_urbanity": -0.11116751388480223,
                "w_dense_urban_neighbourhoods": -0.02614540299183963,
                "w_dense_residential_neighbourhoods": -0.04824578109013244,
                "w_connected_residential_neighbourhoods": 0.007686858438737855,
                "w_gridded_residential_quarters": -0.050103015599959784,
                "w_accessible_suburbia": -0.050112139174123736,
                "w_disconnected_suburbia": -0.027377693952958176,
                "w_open_sprawl": 0.004979426999784998,
                "w_warehouse_park_land": 0.07789540862610816,
                "w_urban_buffer": -0.04099003828527754,
                "w_countryside_agriculture": -0.08228501845331923,
                "w_wild_countryside": -0.08991053056988893
            },
            {
                "urbanity": -0.23776486111690417,
                "dense_urban_neighbourhoods": -0.08060938645847193,
                "dense_residential_neighbourhoods": -0.0701107138924076,
                "connected_residential_neighbourhoods": -0.08511163343414822,
                "gridded_residential_quarters": -0.16178490311534907,
                "accessible_suburbia": -0.10413148329151603,
                "disconnected_suburbia": -0.06010997926100475,
                "open_sprawl": -0.13963681746152964,
                "warehouse_park_land": -0.11537558339101392,
                "urban_buffer": -0.006281680847943349,
                "countryside_agriculture": 0.12047979721745374,
                "wild_countryside": -0.31567177566962323,
                "w_urbanity": -0.27127820770606026,
                "w_dense_urban_neighbourhoods": -0.09667068151131461,
                "w_dense_residential_neighbourhoods": -0.09008668899969931,
                "w_connected_residential_neighbourhoods": -0.10136513632989479,
                "w_gridded_residential_quarters": -0.19426212911051388,
                "w_accessible_suburbia": -0.12376452984179992,
                "w_disconnected_suburbia": -0.07183886793639857,
                "w_open_sprawl": -0.14158655803980807,
                "w_warehouse_park_land": -0.1404608893849856,
                "w_urban_buffer": -0.0303258870518931,
                "w_countryside_agriculture": 0.09975805061024395,
                "w_wild_countryside": -0.3984487609442492
            },
            {
                "urbanity": -0.08167104735929463,
                "dense_urban_neighbourhoods": -0.031070949822645248,
                "dense_residential_neighbourhoods": -0.025468521872342564,
                "connected_residential_neighbourhoods": 0.10161578054467653,
                "gridded_residential_quarters": -0.031368327236938116,
                "accessible_suburbia": -0.007416890380586077,
                "disconnected_suburbia": -0.0409086791953091,
                "open_sprawl": -0.027673111237782065,
                "warehouse_park_land": -0.034834199216917605,
                "urban_buffer": -0.05164489230752118,
                "countryside_agriculture": -0.05301243104299965,
                "wild_countryside": -0.08449895425268479,
                "w_urbanity": -0.036873814766355824,
                "w_dense_urban_neighbourhoods": -0.004336238021630027,
                "w_dense_residential_neighbourhoods": -0.0008292832956728094,
                "w_connected_residential_neighbourhoods": 0.10203856426854237,
                "w_gridded_residential_quarters": 0.0032125033897157074,
                "w_accessible_suburbia": 0.012658043319111389,
                "w_disconnected_suburbia": -0.017743028340347928,
                "w_open_sprawl": -0.015814948835629453,
                "w_warehouse_park_land": -0.0038218274780979803,
                "w_urban_buffer": -0.002095307897928939,
                "w_countryside_agriculture": -0.01615829351386953,
                "w_wild_countryside": -0.01143901397382483
            },
            {
                "urbanity": 0.009133227880404913,
                "dense_urban_neighbourhoods": 0.0011035972563776916,
                "dense_residential_neighbourhoods": -0.025033844544069598,
                "connected_residential_neighbourhoods": -0.009234242207358957,
                "gridded_residential_quarters": -0.0029554494420557464,
                "accessible_suburbia": -0.006837074751574678,
                "disconnected_suburbia": 0.010383648325263967,
                "open_sprawl": 0.0333761983216879,
                "warehouse_park_land": 0.020088601431825923,
                "urban_buffer": 0.1593480221751337,
                "countryside_agriculture": 0.14678133591440895,
                "wild_countryside": 0.01873953088323767,
                "w_urbanity": -0.08381169232624026,
                "w_dense_urban_neighbourhoods": -0.029050434477475285,
                "w_dense_residential_neighbourhoods": -0.05488062044941236,
                "w_connected_residential_neighbourhoods": -0.045195785116096475,
                "w_gridded_residential_quarters": -0.04390246296002106,
                "w_accessible_suburbia": -0.015667550296770597,
                "w_disconnected_suburbia": 0.004483748504883278,
                "w_open_sprawl": 0.007265374265333995,
                "w_warehouse_park_land": -0.023525011136556067,
                "w_urban_buffer": 0.03232571130090189,
                "w_countryside_agriculture": -0.0008445422368417871,
                "w_wild_countryside": -0.15435350132902248
            },
            {
                "urbanity": -0.040656921880672256,
                "dense_urban_neighbourhoods": -0.04176628297098191,
                "dense_residential_neighbourhoods": -0.011697240173147485,
                "connected_residential_neighbourhoods": -0.03534230662030894,
                "gridded_residential_quarters": 0.004049126688171667,
                "accessible_suburbia": 0.15431540826513246,
                "disconnected_suburbia": -0.027128091913913598,
                "open_sprawl": 0.014567803128422367,
                "warehouse_park_land": -0.04367257847311792,
                "urban_buffer": -0.05508111254232676,
                "countryside_agriculture": -0.06301446589627463,
                "wild_countryside": -0.05890878468741993,
                "w_urbanity": -0.14766646981211,
                "w_dense_urban_neighbourhoods": -0.09099067947633555,
                "w_dense_residential_neighbourhoods": -0.041750437557873554,
                "w_connected_residential_neighbourhoods": -0.05546350044474222,
                "w_gridded_residential_quarters": -0.07270757255511871,
                "w_accessible_suburbia": 0.08335904858685755,
                "w_disconnected_suburbia": -0.07814130805105998,
                "w_open_sprawl": -0.02693735351427426,
                "w_warehouse_park_land": -0.0646734136692322,
                "w_urban_buffer": -0.09438615306055179,
                "w_countryside_agriculture": -0.11538844012313472,
                "w_wild_countryside": -0.16546785187457005
            },
            {
                "urbanity": -0.028640999814731387,
                "dense_urban_neighbourhoods": -0.043974815062811194,
                "dense_residential_neighbourhoods": -0.007172402640595568,
                "connected_residential_neighbourhoods": -0.03518663016918509,
                "gridded_residential_quarters": -0.007445246884991646,
                "accessible_suburbia": -0.004489096724937479,
                "disconnected_suburbia": 0.04405704125177019,
                "open_sprawl": 0.13163785832143912,
                "warehouse_park_land": 0.007529493253609162,
                "urban_buffer": -0.0524484893244626,
                "countryside_agriculture": -0.01280083404988744,
                "wild_countryside": -0.02966205274172793,
                "w_urbanity": -0.11473408508564152,
                "w_dense_urban_neighbourhoods": -0.058151100934873974,
                "w_dense_residential_neighbourhoods": -0.025779427661662573,
                "w_connected_residential_neighbourhoods": -0.057299726710298086,
                "w_gridded_residential_quarters": -0.055010434576484725,
                "w_accessible_suburbia": -0.045820995096221506,
                "w_disconnected_suburbia": 0.01904429452529134,
                "w_open_sprawl": 0.09647069834929872,
                "w_warehouse_park_land": -0.03525044055249288,
                "w_urban_buffer": -0.07908270925479256,
                "w_countryside_agriculture": -0.08356905570086542,
                "w_wild_countryside": -0.110290132934657
            },
            {
                "urbanity": -0.029117773467475926,
                "dense_urban_neighbourhoods": -0.0175449244765938,
                "dense_residential_neighbourhoods": -0.005339291309277168,
                "connected_residential_neighbourhoods": -0.015958914515807256,
                "gridded_residential_quarters": -0.014002622596221133,
                "accessible_suburbia": -0.027971207615485404,
                "disconnected_suburbia": 0.12653988465666144,
                "open_sprawl": -0.01933131020535482,
                "warehouse_park_land": -0.008628168623498725,
                "urban_buffer": -0.022745907743562072,
                "countryside_agriculture": -0.027142035838280718,
                "wild_countryside": -0.030903005750345207,
                "w_urbanity": -0.05673459504732817,
                "w_dense_urban_neighbourhoods": -0.01793851792607553,
                "w_dense_residential_neighbourhoods": -0.027908221228745523,
                "w_connected_residential_neighbourhoods": -0.02260585204534197,
                "w_gridded_residential_quarters": -0.03432292399765335,
                "w_accessible_suburbia": -0.027035245930397554,
                "w_disconnected_suburbia": 0.07159851161032958,
                "w_open_sprawl": -0.001337369106487989,
                "w_warehouse_park_land": -0.01434276230824605,
                "w_urban_buffer": -0.04175942818612875,
                "w_countryside_agriculture": -0.03113717369215785,
                "w_wild_countryside": -0.047669882225717955
            }
        ],
        "scale_x": true,
        "log_x": true
    }
}